async_node/__init__.py
async_node/_dynamic_io_executor.py
async_node/_functional_types.py
async_node/async_node.py
async_node/decorators.py
async_node/schedulers.py
async_node-2.0.0.dist-info/METADATA
async_node-2.0.0.dist-info/WHEEL
async_node-2.0.0.dist-info/top_level.txt
async_node-2.0.0.dist-info/RECORD
