Metadata-Version: 2.4
Name: async-node
Version: 2.0.0
Summary: Add your description here
Requires-Python: >=3.13
Requires-Dist: loky>=3.5.6
